{
  "dependencies": [
    "nether"
  ],
  "tasks": {},
  "rewards": {},
  "display": {
    "subtitle": {
      "translate": "quests.nether.nether_fortress.sub"
    },
    "description": [],
    "groups": {
      "Nether": {
        "position": [
          -342,
          -137
        ]
      }
    },
    "icon": {
      "item": {
        "id": "minecraft:nether_bricks",
        "count": 1
      },
      "type": "heracles:item"
    },
    "icon_background": "heracles:textures/gui/quest_backgrounds/default.png",
    "title": {
      "translate": "quests.nether.nether_fortress.name"
    }
  },
  "settings": {
    "showDependencyArrow": true,
    "repeatable": false,
    "autoClaimRewards": false,
    "individual_progress": false,
    "hidden": "LOCKED",
    "unlockNotification": false
  }
}